joke_business_prog/__init__.py
joke_business_prog/__main__.py
joke_business_prog-0.1.0.dist-info/METADATA
joke_business_prog-0.1.0.dist-info/WHEEL
joke_business_prog-0.1.0.dist-info/top_level.txt
joke_business_prog-0.1.0.dist-info/RECORD
