Metadata-Version: 2.1
Name: joke_business_prog
Version: 0.1.0
Summary: Описание моего Python-пакета
Author-email: Pablo_3_16 <p.ergle@centraluniversity.ru>
License: MIT
Requires-Python: >=3.12
